llamero/__init__.py
llamero/__main__.py
llamero/dir2doc.py
llamero/tree_generator.py
llamero/utils.py
llamero/summary/__init__.py
llamero/summary/concatenative.py
llamero/summary/python_files.py
llamero/summary/python_signatures.py
llamero/summary/readmes.py
llamero-0.2.5.dist-info/LICENSE
llamero-0.2.5.dist-info/METADATA
llamero-0.2.5.dist-info/WHEEL
llamero-0.2.5.dist-info/entry_points.txt
llamero-0.2.5.dist-info/top_level.txt
llamero-0.2.5.dist-info/RECORD
