Metadata-Version: 2.1
Name: llamero
Version: 0.2.5
Summary: Tools to facilitate collaborating with LLMs
License: MIT License
Requires-Python: >=3.11
License-File: LICENSE
Requires-Dist: Jinja2>=3.1.2
Requires-Dist: tomli>=2.0.1
Requires-Dist: loguru>=0.7.0
Requires-Dist: fire>=0.5.0
Requires-Dist: tree-format>=0.1.2
Requires-Dist: pytest>=7.0
Requires-Dist: markdown2>=2.4.0
